CHANGES.txt
MANIFEST.in
README.txt
TODO.txt
setup.cfg
setup.py
anybox/__init__.py
anybox.funkload.openerp.egg-info/PKG-INFO
anybox.funkload.openerp.egg-info/SOURCES.txt
anybox.funkload.openerp.egg-info/dependency_links.txt
anybox.funkload.openerp.egg-info/namespace_packages.txt
anybox.funkload.openerp.egg-info/not-zip-safe
anybox.funkload.openerp.egg-info/requires.txt
anybox.funkload.openerp.egg-info/top_level.txt
anybox/funkload/__init__.py
anybox/funkload/openerp/__init__.py
anybox/funkload/openerp/testcase.py