Metadata-Version: 1.1
Name: anybox.funkload.openerp
Version: 0.2
Summary: Base classes for functional and load testing of OpenERP with Funkload
Home-page: https://launchpad.net/anybox.funkload.openerp
Author: Georges Racinet
Author-email: gracinet@anybox.fr
License: GPLv3
Platform: UNKNOWN
Classifier: License :: OSI Approved :: GNU General Public License v3 or later (GPLv3+)
Classifier: Topic :: Software Development :: Quality Assurance
Classifier: Topic :: Software Development :: Testing
Classifier: Topic :: System :: Benchmark
